<ItacAcademyItem AcademyId="0008" RecordId="021-000000655"><Name>Confusi-Bologna (Accademia dei)</Name><City CityId="1"><CityItalianName>Bologna</CityItalianName><CityEnglishName>Bologna</CityEnglishName><CityLatinName>Bononiae</CityLatinName></City><EmblemDescription>Chaos</EmblemDescription><Motto>Ante</Motto><StartDate>1570</StartDate><EndDate>?</EndDate><DateText>1570-?</DateText><Notes>Dates of this Academy, and names of members are in Maylender, vol. II, p. 75.</Notes><ItacPersonItem PersonId="5292" RecordId="022-000000340"><Name>de` Rossi dei Conti di Pontecchio,Giovanni Galeazzo, Count, </Name><Nickname>Il Disposto</Nickname><Motto /><PersonEmblemDescription /></ItacPersonItem><ItacPersonItem PersonId="5602" RecordId="022-000000659"><Name>Manfredi, Muzio , , </Name><Nickname>Il Vinto</Nickname><Motto /><PersonEmblemDescription /></ItacPersonItem><ItacPersonItem PersonId="5640" RecordId="022-000000715"><Name>Peruzzini, Ippolito , , </Name><Nickname>Lo Stanco</Nickname><Motto>Haec meta laborum</Motto><PersonEmblemDescription>An olive tree and a dove</PersonEmblemDescription></ItacPersonItem><ItacPersonItem PersonId="17704" RecordId="022-000004600"><Name>Guidiccioni,Cristoforo,,</Name><Nickname /><Motto /><PersonEmblemDescription /></ItacPersonItem><ItacPersonItem PersonId="17705" RecordId="022-000004601"><Name>Boncompagni,Girolamo,,</Name><Nickname /><Motto /><PersonEmblemDescription /></ItacPersonItem><ItacPersonItem PersonId="17706" RecordId="022-000004602"><Name>Campeggi,Giambattista,Bishop of Mallorca,1507 - 1583</Name><Nickname /><Motto /><PersonEmblemDescription /></ItacPersonItem><ItacPersonItem PersonId="17707" RecordId="022-000004603"><Name>Legnani,Antonio,,</Name><Nickname /><Motto /><PersonEmblemDescription /></ItacPersonItem><ItacPersonItem PersonId="17708" RecordId="022-000004604"><Name>Grassi,Fulvio,,</Name><Nickname /><Motto /><PersonEmblemDescription /></ItacPersonItem><ItacPersonItem PersonId="17709" RecordId="022-000004605"><Name>Grimaldi,Francesco,,</Name><Nickname /><Motto /><PersonEmblemDescription /></ItacPersonItem><ItacPersonItem PersonId="17710" RecordId="022-000004606"><Name>Visconte,Ottavio,,</Name><Nickname /><Motto /><PersonEmblemDescription /></ItacPersonItem><ItacPersonItem PersonId="17711" RecordId="022-000004607"><Name>Fiorenza,Giovanni Battista,,</Name><Nickname /><Motto /><PersonEmblemDescription /></ItacPersonItem><ItacPersonItem PersonId="5601" RecordId="022-000000657"><Name>Colonna,Giulio Cesare,Prince of Palestrina,fl. 1571</Name><Nickname /><Motto /><PersonEmblemDescription /></ItacPersonItem><ItacPersonItem PersonId="5639" RecordId="022-000000714"><Name>Simonetti,Cesare,,</Name><Nickname>L` Assordato</Nickname><Motto /><PersonEmblemDescription /></ItacPersonItem><Citation>Lorenza Gianfrancesco and Simone Testa, directed by Jane Everson, Denis Reidy, Lisa Sampson, assisted by Thomas Denman, for the Italian Academies Database project.</Citation></ItacAcademyItem>