<ItacAcademyItem AcademyId="0234" RecordId="021-000006861"><Name>Inariditi (Accademia degli)</Name><City CityId="45"><CityItalianName>Roma</CityItalianName><CityEnglishName>Rome</CityEnglishName><CityLatinName>Romae</CityLatinName></City><EmblemDescription>Tree trunk almost without leaves</EmblemDescription><Motto>In pignore viret</Motto><Citation>Lorenza Gianfrancesco and Simone Testa, directed by Jane Everson, Denis Reidy, Lisa Sampson, assisted by Thomas Denman, for the Italian Academies Database project.</Citation></ItacAcademyItem>