<ItacWorkItem RecordId="023-000008671" WorkId="000991"><ShortTitle>Le pompe dell`Accademia del disegno</ShortTitle><LongTitle>Solennemente celebrate nel Campidoglioil di` 25 Febraro 1702. Descritte d Giuseppe Ghezzi pittore e segretario di essa. Dedicate dagli Academci alla santita` di nostro signore Clemente undecimo Pontefice Ottimo Massimo</LongTitle><ItacAcademyItem AcademyId="0493" RecordID="021-000008025">Disegno (Accademia del)</ItacAcademyItem><Shelfmark>561c9</Shelfmark><Language>Italian</Language><Marginalia>No</Marginalia><TitlePageImage ImageId="55339">023-000008671_55339_3.jpg</TitlePageImage><Citation>Lorenza Gianfrancesco and Simone Testa, directed by Jane Everson, Denis Reidy, Lisa Sampson, assisted by Thomas Denman, for the Italian Academies Database project.</Citation></ItacWorkItem>