<ItacWorkItem RecordId="023-000008645" WorkId="000978"><ShortTitle>Mandatum Academiae Venetae Ab. Marlup</ShortTitle><ItacAcademyItem AcademyId="0471" RecordID="021-000007881">Veneziana (Academia)</ItacAcademyItem><Format>4&#176;</Format><City CityId="35"><PublicationPlaceItalianName>Venezia</PublicationPlaceItalianName><PublicationPlaceEnglishName>Venice</PublicationPlaceEnglishName><PublicationPlaceLatinName>Venetiae</PublicationPlaceLatinName></City><PublicationYear>1558</PublicationYear><DedicationPlaceDate>Document dated 23 February 1558</DedicationPlaceDate><Shelfmark>John Rylands Library Aldine Collection 547</Shelfmark><Content>Instructions given to Abbot Marlupino to take care of the Academy`s commercial interests in Francfort and other parts of Germany</Content><Language>Latin</Language><Pagination>4 leaves not numbered</Pagination><Marginalia>No</Marginalia><Citation>Lorenza Gianfrancesco and Simone Testa, directed by Jane Everson, Denis Reidy, Lisa Sampson, assisted by Thomas Denman, for the Italian Academies Database project.</Citation></ItacWorkItem>