<ItacWorkItem RecordId="023-000001812" WorkId="00128"><ShortTitle>Der fu?rtefflichen ... Jungfer Gabrielis Carola Patinin </ShortTitle><LongTitle>u?ber die glu?cklich entsetzte ... Residentz-Stadt Wien auf der Italia?nischen Academie Padua in Lat. Sprach gehaltene ... Lob-Rede ... in das Teutsche ... uebersetzet. Lat. &amp; Germ</LongTitle><ItacAcademyItem AcademyId="0021" RecordID="021-000001570">Academia dei Ricovrati</ItacAcademyItem><Format>10&#176;</Format><City CityId="58"><PublicationPlaceItalianName>Francoforte</PublicationPlaceItalianName><PublicationPlaceEnglishName>Frankfort</PublicationPlaceEnglishName><PublicationPlaceLatinName>Fancofurtii</PublicationPlaceLatinName></City><PublicationYear>1684</PublicationYear><Shelfmark>1315.a.15</Shelfmark><Subjects>Encomiastic discourse on the Turkish menace</Subjects><Language>Latin|German</Language><Illustration>Engraving | The author`s portrait</Illustration><Pagination>pp. 38</Pagination><Marginalia>No</Marginalia><Authors><ItacPersonItem PersonId="9162" RecordID="022-000001739">Patina,Carola Catterina,,ca 1667-1745</ItacPersonItem></Authors><Notes>According to Vigan&#242; `Le donne e i Ricovrati` in L`Accademia in biblioteca (2004) p. 206 this could be Gabrielle`s German translation of her sister`s speech.</Notes><Citation>Lorenza Gianfrancesco and Simone Testa, directed by Jane Everson, Denis Reidy, Lisa Sampson, assisted by Thomas Denman, for the Italian Academies Database project.</Citation></ItacWorkItem>