<ItacWorkItem RecordId="023-000005158" WorkId="000635"><ShortTitle>Crispo</ShortTitle><LongTitle>Tragedia Del P. Bernardino Stefonio della compagnia di Gies&#249;. Trasportata dal latino nel nostro volgare Da Gioseppe Caropreso Nobile Napolitano All`Illustrissimo il Signore D. Fabritio Ruffo Conte De Sinopoli e Borrello </LongTitle><ItacAcademyItem AcademyId="0017" RecordID="021-000001040">Academia degli Oziosi</ItacAcademyItem><Format>8&#186;</Format><City CityId="2"><PublicationPlaceItalianName>Napoli    </PublicationPlaceItalianName><PublicationPlaceEnglishName>Naples</PublicationPlaceEnglishName><PublicationPlaceLatinName>Neapoli</PublicationPlaceLatinName></City><PublicationYear>1615</PublicationYear><DedicationPlaceDate>Naples 25 August 1615</DedicationPlaceDate><Shelfmark>1578/4490</Shelfmark><Subjects>Tragedy</Subjects><Language>Italian|Latin</Language><Illustration>Engraved title page|</Illustration><Pagination>pp. 183</Pagination><Marginalia>No</Marginalia><Authors><ItacPersonItem PersonId="18179" RecordID="022-000005156">Stefonio,Bernardino,,1560 - 1620</ItacPersonItem></Authors><Contributors><ItacPersonItem PersonId="15002" RecordID="022-000001044">Basile,Giovan Battista,Count of Torone,1575-1632</ItacPersonItem><ItacPersonItem PersonId="16641" RecordID="022-000003362">Pinto ,Carlo,,</ItacPersonItem></Contributors><Censors><ItacPersonItem PersonId="15222" RecordID="022-000001264">Boschius,Alexander,General Vicar ,</ItacPersonItem><ItacPersonItem PersonId="15224" RecordID="022-000001266">Longus,Ioannes,Canon|Archbishop of Naples,</ItacPersonItem></Censors><CensorsAgreement>Imprimatur.
Alexander Boschius Vicarius Generalis. 
Ioannes Longus Canonicus, &amp; Curiae Archiepiscop. Neap. Theolog. Dep. vidit, reg. fol. 30.</CensorsAgreement><Dedicatees><ItacPersonItem PersonId="18182" RecordID="022-000005161">Ruffo,Fabritio,Count of Sinopoli and Borrello,</ItacPersonItem><ItacPersonItem PersonId="18183" RecordID="022-000005162">Ruffo,Vincenzo,Prince of Scilla,</ItacPersonItem><ItacPersonItem PersonId="18181" RecordID="022-000005160">Caropreso,Giuseppe,,</ItacPersonItem><ItacPersonItem PersonId="18179" RecordID="022-000005156">Stefonio,Bernardino,,1560 - 1620</ItacPersonItem></Dedicatees><Editors><ItacPersonItem PersonId="18181" RecordID="022-000005160">Caropreso,Giuseppe,,</ItacPersonItem></Editors><Printers><ItacPersonItem PersonId="17469" RecordID="022-000004338">Carlino &amp; Vitale ,Giovanni Giacomo &amp; Costantino,,</ItacPersonItem></Printers><Essays><Essay><EssayTitle>Sonetto De L`Autore Al Medesimo Illustriss. Signor Conte  </EssayTitle><Contributor><ItacPersonItem PersonId="18181" RecordID="022-000005160">Caropreso,Giuseppe,,</ItacPersonItem></Contributor></Essay><Essay><EssayTitle>Ottava De L`Autore All`Illustrissimo, &amp; Eccellentissimo Sig. Il Signor Don Vincenzo Ruffo. Principe Di Scilla, &amp;c.</EssayTitle><Contributor><ItacPersonItem PersonId="18181" RecordID="022-000005160">Caropreso,Giuseppe,,</ItacPersonItem></Contributor></Essay><Essay><EssayTitle>Prognostico De L`Autore Al medesimo Illustrissimo Signor Conte</EssayTitle><Contributor><ItacPersonItem PersonId="18181" RecordID="022-000005160">Caropreso,Giuseppe,,</ItacPersonItem></Contributor></Essay><Essay><EssayTitle>Del Cavalier Basile, Academico Otioso. Al Signor Gioseppe Caropreso</EssayTitle><Contributor><ItacPersonItem PersonId="15002" RecordID="022-000001044">Basile,Giovan Battista,Count of Torone,1575-1632</ItacPersonItem></Contributor></Essay><Essay><EssayTitle>In Tragaediam Crispi Italicae dialecto datam &#224; praeclato viro Iosepho Caropreso Neapolitano. Caroli Pinti Academici Otiosi ODE.</EssayTitle><Contributor><ItacPersonItem PersonId="16641" RecordID="022-000003362">Pinto ,Carlo,,</ItacPersonItem></Contributor></Essay></Essays><Citation>Lorenza Gianfrancesco and Simone Testa, directed by Jane Everson, Denis Reidy, Lisa Sampson, assisted by Thomas Denman, for the Italian Academies Database project.</Citation></ItacWorkItem>