<ItacWorkItem RecordId="023-000001450" WorkId="00178"><ShortTitle>Le Rime Spirituali</ShortTitle><LongTitle>Del P. F. Arcangelo Spina Eremita Camaldolese Dedicate All`Illustriss. E R.mo Signor Cardinale Scipione Borghese</LongTitle><ItacAcademyItem AcademyId="0017" RecordID="021-000001040">Academia degli Oziosi</ItacAcademyItem><Format>4&#186;</Format><City CityId="2"><PublicationPlaceItalianName>Napoli</PublicationPlaceItalianName><PublicationPlaceEnglishName>Naples</PublicationPlaceEnglishName><PublicationPlaceLatinName>Neapoli</PublicationPlaceLatinName></City><PublicationYear>1616</PublicationYear><DedicationPlaceDate>Naples 7 September 1616</DedicationPlaceDate><Shelfmark>c.46.e.14.</Shelfmark><Content>Religious Poetry | Encomiastic Poetry</Content><Subjects>Religious Poetry|Encomiastic Poetry</Subjects><Language>Latin|Italian</Language><Illustration>A plate on the title page showing two religious figures. At the top an image of Christ raising his hand in blessing. | In the center the coat of arms of the Borghese  family [an eagle and a dragon] is displayed. | At the bottom the letters AB may refer to the engraver|</Illustration><Pagination>First 12 pages unnumbered | Last 22 pages unnumbered | pp. 255</Pagination><Marginalia>No</Marginalia><Authors><ItacPersonItem PersonId="15037" RecordID="022-000001079">Spina,E. Arcangelo,,</ItacPersonItem></Authors><Contributors><ItacPersonItem PersonId="15017" RecordID="022-000001059">Carafa,Luigi,Prince of Stigliano,1567 - 1630</ItacPersonItem><ItacPersonItem PersonId="15086" RecordID="022-000001127">Pignatelli,Ettore,,</ItacPersonItem><ItacPersonItem PersonId="15208" RecordID="022-000001250">Brancaccio,Francesco Maria,Cardinal,1592-1675</ItacPersonItem><ItacPersonItem PersonId="16683" RecordID="022-000003416">Romano,Fabio,,</ItacPersonItem><ItacPersonItem PersonId="16684" RecordID="022-000003417">Morra ,Goffredo,,</ItacPersonItem><ItacPersonItem PersonId="16685" RecordID="022-000003418">Amabile,Mutio,,</ItacPersonItem><ItacPersonItem PersonId="15345" RecordID="022-000001384">Ferrari,Francesco,,</ItacPersonItem></Contributors><Publishers><ItacPersonItem PersonId="15209" RecordID="022-000001251">Roncagliolo,Gio. Domenico,,</ItacPersonItem></Publishers><Notes>This text contains verses to various Oziosi academicians</Notes><Censors><ItacPersonItem PersonId="15139" RecordID="022-000001181">Ghibertus,Petrus Anton[ius],,</ItacPersonItem><ItacPersonItem PersonId="15224" RecordID="022-000001266">Longus,Ioannes,Canon|Archbishop of Naples,</ItacPersonItem></Censors><CensorsAgreement>Imprimatur. Petrus Ant. Ghibertus Vic. General. Neapo. Ioannes Longus Can. &amp; Cur. Archiep. Neap. Theol.</CensorsAgreement><Dedicatees><ItacPersonItem PersonId="7703" RecordID="022-000001478">Borghese-Caffarelli,Scipione,Cardinal,1576 - 1633</ItacPersonItem></Dedicatees><Illustrators><ItacPersonItem PersonId="15353" RecordID="022-000001392">A,B,,</ItacPersonItem></Illustrators><EngraverReference>Y</EngraverReference><TitlePageImage ImageId="53925">023-000001450_53925_3.jpg</TitlePageImage><Essays><Essay><EssayTitle>Al Signor D. Pietro di Castro Conte di Lemos, Vicere` di Napoli.</EssayTitle><Contributor><ItacPersonItem PersonId="" RecordID="" /></Contributor></Essay><Essay><EssayTitle>In morte del Sig. D. Filippo Caetano Duca di Sermoneta.</EssayTitle><Contributor><ItacPersonItem PersonId="" RecordID="" /></Contributor></Essay><Essay><EssayTitle>Al Sig. Gio. Battista Manso principe dell`Accademia de gli otiosi.</EssayTitle><Contributor><ItacPersonItem PersonId="" RecordID="" /></Contributor></Essay><Essay><EssayTitle>Al P. Angelo Grillo</EssayTitle><Contributor><ItacPersonItem PersonId="" RecordID="" /></Contributor></Essay><Essay><EssayTitle>Al P. Marcello Macedonio</EssayTitle><Contributor><ItacPersonItem PersonId="" RecordID="" /></Contributor></Essay><Essay><EssayTitle>Al P. Girolamo d`Afflitto</EssayTitle><Contributor><ItacPersonItem PersonId="" RecordID="" /></Contributor></Essay><Essay><EssayTitle>In morte del Sig. D. Giovanni Lopez</EssayTitle><Contributor><ItacPersonItem PersonId="" RecordID="" /></Contributor></Essay><Essay><EssayTitle>Al Sig. Francesco de Petris</EssayTitle><Contributor><ItacPersonItem PersonId="" RecordID="" /></Contributor></Essay><Essay><EssayTitle>Del Signor D. Luigi Carrafa Principe di Stigliano all`autore.</EssayTitle><Contributor><ItacPersonItem PersonId="15017" RecordID="022-000001059">Carafa,Luigi,Prince of Stigliano,</ItacPersonItem></Contributor></Essay><Essay><EssayTitle>Del Signor D. Hettorre Pignatelli</EssayTitle><Contributor><ItacPersonItem PersonId="15086" RecordID="022-000001127">Pignatelli,Ettore,,</ItacPersonItem></Contributor></Essay><Essay><EssayTitle>Del Sig. Francesco Maria Brancaccio</EssayTitle><Contributor><ItacPersonItem PersonId="15208" RecordID="022-000001250">Brancaccio,Francesco Maria,Cardinal,1592-1675</ItacPersonItem></Contributor></Essay><Essay><EssayTitle>Del Signor Fabio Romano</EssayTitle><Contributor><ItacPersonItem PersonId="16683" RecordID="022-000003416">Romano,Fabio,,</ItacPersonItem></Contributor></Essay><Essay><EssayTitle>Del Signor Francesco Ferrari</EssayTitle><Contributor><ItacPersonItem PersonId="5606" RecordID="022-000000672">Ferrari,Francesco,,</ItacPersonItem></Contributor></Essay><Essay><EssayTitle>Del Sig. Goffredo Morra</EssayTitle><Contributor><ItacPersonItem PersonId="16684" RecordID="022-000003417">Morra ,Goffredo,,</ItacPersonItem></Contributor></Essay><Essay><EssayTitle>Del Signor Mutio Amabile</EssayTitle><Contributor><ItacPersonItem PersonId="16685" RecordID="022-000003418">Amabile,Mutio,,</ItacPersonItem></Contributor></Essay></Essays><Citation>Lorenza Gianfrancesco and Simone Testa, directed by Jane Everson, Denis Reidy, Lisa Sampson, assisted by Thomas Denman, for the Italian Academies Database project.</Citation></ItacWorkItem>