<ItacPersonItem PersonId="18305" RecordId="022-000005313"><Surname>Ramignani</Surname><Forename>Marcello</Forename><Gender>Male</Gender><AlternativeName><AlternativeSurname>Ramignano</AlternativeSurname><AlternativeForename> Marcello</AlternativeForename></AlternativeName><Nationality NationalityId="139">of Chieti</Nationality><Notes>Marcello Ramignani became a member of the Oziosi academy in Naples in December 1613. See Girolamo Nicolino, Historia della Citta di Chieti, Napoli, Honofrio Savio, 1657 (BL Shelfmark: 10131.c.9.) </Notes><Role /><Citation>Lorenza Gianfrancesco and Simone Testa, directed by Jane Everson, Denis Reidy, Lisa Sampson, assisted by Thomas Denman, for the Italian Academies Database project.</Citation></ItacPersonItem>