<ItacPersonItem PersonId="20233" RecordId="022-000007813"><Surname>Natolini</Surname><Forename>Giovanni Battista</Forename><DateText>1551-1609</DateText><StartDate>1551</StartDate><EndDate>1609</EndDate><Nationality NationalityId="188">of San Daniele (Udine)</Nationality><Notes>Dates an provenance according to the biography by Lorenzo Carpane`, in DBI. </Notes><Role>Printer</Role><Citation>Lorenza Gianfrancesco and Simone Testa, directed by Jane Everson, Denis Reidy, Lisa Sampson, assisted by Thomas Denman, for the Italian Academies Database project.</Citation></ItacPersonItem>