<ItacPersonItem PersonId="17187" RecordId="022-000003994"><Surname>Ghislieri</Surname><Forename>Michele</Forename><Gender>Male</Gender><PersonalTitle>Cardinal Alessandrino|Pope Pius V</PersonalTitle><DateText>1504-1572</DateText><StartDate>1504</StartDate><EndDate>1572</EndDate><Nationality NationalityId="363">of Bosco (Alessandria)</Nationality><Notes>Patron of the Accademia Veneziana</Notes><Role>Dedicatee</Role><Citation>Lorenza Gianfrancesco and Simone Testa, directed by Jane Everson, Denis Reidy, Lisa Sampson, assisted by Thomas Denman, for the Italian Academies Database project.</Citation></ItacPersonItem>