<ItacPersonItem PersonId="15200" RecordId="022-000001169"><Surname>Filomarino</Surname><Forename>Ascanio</Forename><AlternativeName><AlternativeSurname>Philomarino</AlternativeSurname><AlternativeForename>Ascanio</AlternativeForename></AlternativeName><AlternativeName><AlternativeSurname>Filomarino</AlternativeSurname><AlternativeForename> Ascanius</AlternativeForename></AlternativeName><PersonalTitle>Cardinal|Archbishop</PersonalTitle><DateText>1583-1666</DateText><StartDate>1583</StartDate><EndDate>1666</EndDate><Nationality NationalityId="57">Italian</Nationality><Role>Censor|Dedicatee</Role><Gender>Male</Gender><Citation>Lorenza Gianfrancesco and Simone Testa, directed by Jane Everson, Denis Reidy, Lisa Sampson, assisted by Thomas Denman, for the Italian Academies Database project.</Citation></ItacPersonItem>