<ItacPersonItem PersonId="7402" RecordId="022-000000993"><PersonalTitle /><DateText /><Nickname /><Pseudonym /><Anagram /><Notes /><EngraverReference /><TypographicReference /><Surname>Contarini</Surname><Forename>Giulio</Forename><StartDate /><EndDate /><Nationality>Italian</Nationality><Role>Dedicatee</Role><Gender>Male</Gender><Citation>Lorenza Gianfrancesco and Simone Testa, directed by Jane Everson, Denis Reidy, Lisa Sampson, assisted by Thomas Denman, for the Italian Academies Database project.</Citation></ItacPersonItem>