<ItacPersonItem PersonId="16689" RecordId="022-000003425"><Surname>Anton Maria</Surname><Gender>Male</Gender><DateText>?-1550</DateText><StartDate>?</StartDate><EndDate>1550</EndDate><Nationality NationalityId="89">Sienese</Nationality><Notes>`Cartaio`, Anton Maria (this is his forename) was among the founders of the Rozzi. In the Colophon of El farfalla he is called `Libraro`.</Notes><Role>Author</Role><Citation>Lorenza Gianfrancesco and Simone Testa, directed by Jane Everson, Denis Reidy, Lisa Sampson, assisted by Thomas Denman, for the Italian Academies Database project.</Citation></ItacPersonItem>