<ItacPersonItem PersonId="5293" RecordId="022-000000341"><Surname>Norii</Surname><Forename>Marino</Forename><Nationality NationalityId="57">Italian</Nationality><Notes>He wrote two poems in Corona di rose poetiche 1590</Notes><Role>Contributor</Role><EngraverReference>N</EngraverReference><Gender>Male</Gender><Citation>Lorenza Gianfrancesco and Simone Testa, directed by Jane Everson, Denis Reidy, Lisa Sampson, assisted by Thomas Denman, for the Italian Academies Database project.</Citation></ItacPersonItem>