<ItacPersonItem PersonId="9128" RecordId="022-000001735"><Surname>Bottazzo</Surname><Forename>Gioan Iacopo</Forename><Gender>Male</Gender><AlternativeName><AlternativeForename> Giovan Jacopo</AlternativeForename></AlternativeName><AlternativeName><AlternativeForename> Giovanni Iacopo</AlternativeForename></AlternativeName><AlternativeName><AlternativeSurname>Bottazzi</AlternativeSurname></AlternativeName><AlternativeName><AlternativeSurname>Bottacio</AlternativeSurname></AlternativeName><AlternativeName><AlternativeSurname>Boccacio</AlternativeSurname></AlternativeName><AlternativeName><AlternativeSurname>Bottaccio</AlternativeSurname></AlternativeName><AlternativeName><AlternativeForename> Giovanni Giacomo</AlternativeForename></AlternativeName><AlternativeName><AlternativeSurname>Bottatti</AlternativeSurname><AlternativeForename> Io. Iacobi</AlternativeForename></AlternativeName><DateText>Early 16th C.</DateText><StartDate>Early 16th C.</StartDate><Nationality NationalityId="369">of Montecastello (Alessandria)</Nationality><Notes>Bottazzo features as a main character in book 4 of Stefano Guazzo`s Civil conversatione (1574) referred to as `Cavalier Bottazzo`. For his biography, see Piero Floriani, `BOTTAZZO, Giovanni Iacopo,` Dizionario Biografico degli Italiani 13 (1974). There are 6 letters by Bottazzo in Stefano Guazzo`s Lettere Volgari di Diversi Gentilhuomini del Monferrato (1566).</Notes><Role>Author|Contributor</Role><Citation>Lorenza Gianfrancesco and Simone Testa, directed by Jane Everson, Denis Reidy, Lisa Sampson, assisted by Thomas Denman, for the Italian Academies Database project.</Citation></ItacPersonItem>