<ItacPersonItem PersonId="19102" RecordId="022-000006229"><Surname>Gonzaga</Surname><Forename>Vincenzo</Forename><Gender>Male</Gender><PersonalTitle>Duke of Mantua</PersonalTitle><DateText>1562-1612</DateText><StartDate>1562</StartDate><EndDate>1612</EndDate><Nationality NationalityId="90">of Mantua</Nationality><Role>Dedicatee</Role><Citation>Lorenza Gianfrancesco and Simone Testa, directed by Jane Everson, Denis Reidy, Lisa Sampson, assisted by Thomas Denman, for the Italian Academies Database project.</Citation></ItacPersonItem>