<ItacPersonItem PersonId="20308" RecordId="022-000007962"><Surname>Maurolico</Surname><Forename>Silvestro</Forename><AlternativeName><AlternativeSurname>Maruli</AlternativeSurname><AlternativeForename> Silvestro</AlternativeForename></AlternativeName><PersonalTitle>Monsignor|Abbot</PersonalTitle><Nationality NationalityId="120">of Messina</Nationality><Notes>For a short biographical account see Antonino Mongitore, Bibliotheca Sicula, Felicella, Palermo, Vol.II, p. 216 (BL Shelfmark:610.m.10.) </Notes><Role>Author|Contributor</Role><Citation>Lorenza Gianfrancesco and Simone Testa, directed by Jane Everson, Denis Reidy, Lisa Sampson, assisted by Thomas Denman, for the Italian Academies Database project.</Citation></ItacPersonItem>