<ItacPersonItem PersonId="20327" RecordId="022-000007989"><Surname>l`Algaria</Surname><Forename>Mariano</Forename><AlternativeName><AlternativeSurname>Algaria</AlternativeSurname><AlternativeForename /></AlternativeName><PersonalTitle>Senator of Palermo</PersonalTitle><Nationality NationalityId="140">Sicilian</Nationality><Role>Dedicatee</Role><Citation>Lorenza Gianfrancesco and Simone Testa, directed by Jane Everson, Denis Reidy, Lisa Sampson, assisted by Thomas Denman, for the Italian Academies Database project.</Citation></ItacPersonItem>