<ItacPersonItem PersonId="19091" RecordId="022-000006216"><Surname>Porcia</Surname><Forename>Bartolomeo</Forename><AlternativeName><AlternativeSurname>Portia</AlternativeSurname><AlternativeForename /></AlternativeName><DateText>1540(?) - 1578</DateText><StartDate>1540(?) </StartDate><EndDate> 1578</EndDate><Nationality NationalityId="193">of Udine</Nationality><Role /><Gender>Male</Gender><Citation>Lorenza Gianfrancesco and Simone Testa, directed by Jane Everson, Denis Reidy, Lisa Sampson, assisted by Thomas Denman, for the Italian Academies Database project.</Citation></ItacPersonItem>