<ItacPersonItem PersonId="6036" RecordId="022-000000741"><Surname>Carracci</Surname><Forename>Lodovico</Forename><Gender>Male</Gender><AlternativeName><AlternativeSurname>Carraccio</AlternativeSurname></AlternativeName><DateText>1555-1619</DateText><StartDate>1555</StartDate><EndDate>1619</EndDate><Nationality NationalityId="81">Bolognese</Nationality><Notes>Portrait from Malvasia, Felsina pittrice, I, p. 354.</Notes><Role /><Citation>Lorenza Gianfrancesco and Simone Testa, directed by Jane Everson, Denis Reidy, Lisa Sampson, assisted by Thomas Denman, for the Italian Academies Database project.</Citation></ItacPersonItem>