<ItacPersonItem PersonId="18772" RecordId="022-000005839"><Surname>Moraldi</Surname><Forename>Santo</Forename><AlternativeName><AlternativeSurname>Moraldi de Bibiena</AlternativeSurname><AlternativeForename> Santis</AlternativeForename></AlternativeName><Nationality NationalityId="266">of Bibiena</Nationality><Role>Contributor</Role><Gender>Male</Gender><Citation>Lorenza Gianfrancesco and Simone Testa, directed by Jane Everson, Denis Reidy, Lisa Sampson, assisted by Thomas Denman, for the Italian Academies Database project.</Citation></ItacPersonItem>