<ItacPersonItem PersonId="17999" RecordId="022-000004935"><Surname>Bascarini</Surname><Forename>Niccolo`</Forename><Gender>Male</Gender><DateText>fl. 1541-1554</DateText><StartDate>fl. 1541</StartDate><EndDate>1554</EndDate><Nationality NationalityId="198">of Pavone di Sabbio Chiese (Brescia)</Nationality><Notes>The dates refer to his activity in Venice </Notes><Role>Editor</Role><Citation>Lorenza Gianfrancesco and Simone Testa, directed by Jane Everson, Denis Reidy, Lisa Sampson, assisted by Thomas Denman, for the Italian Academies Database project.</Citation></ItacPersonItem>