<ItacPersonItem PersonId="7701" RecordId="022-000001476"><PersonalTitle /><DateText /><Nickname /><Pseudonym /><Anagram /><Notes /><EngraverReference /><TypographicReference /><Surname>Vincentium</Surname><Forename>Alexandrum</Forename><StartDate /><EndDate /><Nationality>Italian</Nationality><Role>Printer</Role><Gender>Male</Gender><Citation>Lorenza Gianfrancesco and Simone Testa, directed by Jane Everson, Denis Reidy, Lisa Sampson, assisted by Thomas Denman, for the Italian Academies Database project.</Citation></ItacPersonItem>