<ItacPersonItem PersonId="19590" RecordId="022-000006925"><Surname>Vaccari</Surname><Forename>Giuseppe Antonio</Forename><DateText>1680 - 1717</DateText><StartDate>1680 </StartDate><EndDate> 1717</EndDate><Nationality NationalityId="93">Ferrarese</Nationality><Notes>For his life, and activity within the Accademia dei Disuniti, see Giornale de Letterati, vol. 29, p. 277ff.</Notes><Role /><Gender>Male</Gender><Citation>Lorenza Gianfrancesco and Simone Testa, directed by Jane Everson, Denis Reidy, Lisa Sampson, assisted by Thomas Denman, for the Italian Academies Database project.</Citation></ItacPersonItem>