<ItacPersonItem PersonId="15275" RecordId="022-000001315"><PersonalTitle>Duke</PersonalTitle><DateText /><Nickname /><Pseudonym /><Anagram /><Notes /><EngraverReference>N</EngraverReference><TypographicReference>N</TypographicReference><Surname>Piscicello</Surname><Forename>Fabio</Forename><StartDate /><EndDate /><Nationality>Italian</Nationality><Role>Contributor</Role><Gender>Male</Gender><Citation>Lorenza Gianfrancesco and Simone Testa, directed by Jane Everson, Denis Reidy, Lisa Sampson, assisted by Thomas Denman, for the Italian Academies Database project.</Citation></ItacPersonItem>